pycrossc/Global.py
pycrossc/__init__.py
pycrossc/malloc.py
pycrossc/printf.py
pycrossc/sinit.py
pycrossc/sprintf.py
pycrossc-1.2.2.dist-info/LICENSE.txt
pycrossc-1.2.2.dist-info/METADATA
pycrossc-1.2.2.dist-info/WHEEL
pycrossc-1.2.2.dist-info/top_level.txt
pycrossc-1.2.2.dist-info/RECORD
