Metadata-Version: 2.1
Name: pycrossc
Version: 1.2.2
Summary: Exposing C features to Python, niche and popular
Author-email: WCG847 <heelmods@gmail.com>
License: Apache-2.0
Project-URL: Homepage, https://github.com/wcg847/PyCrossC
Project-URL: Repository, https://github.com/wcg847/PyCrossC
Platform: Windows
Classifier: Operating System :: Microsoft :: Windows
Classifier: Programming Language :: Python :: 3
Classifier: Programming Language :: Python :: 3.8
Classifier: Programming Language :: Python :: 3.9
Classifier: Programming Language :: Python :: 3.10
Classifier: Programming Language :: Python :: 3.11
Classifier: Intended Audience :: Developers
Classifier: License :: OSI Approved :: Apache Software License
Classifier: Topic :: Software Development :: Libraries
Requires-Python: >=3.8
License-File: LICENSE.txt
